fastconvert.py
fastconvert-1.0.5.dist-info/METADATA
fastconvert-1.0.5.dist-info/WHEEL
fastconvert-1.0.5.dist-info/entry_points.txt
fastconvert-1.0.5.dist-info/top_level.txt
fastconvert-1.0.5.dist-info/RECORD
