Metadata-Version: 2.4
Name: fastconvert
Version: 1.0.5
Summary: A powerful CLI tool for converting files between different formats.
Author: qwez
Classifier: Programming Language :: Python :: 3
Classifier: License :: OSI Approved :: MIT License
Classifier: Operating System :: OS Independent
Requires-Python: >=3.6
Requires-Dist: click
Requires-Dist: pillow
Requires-Dist: opencv-python
Dynamic: author
Dynamic: classifier
Dynamic: description
Dynamic: description-content-type
Dynamic: requires-dist
Dynamic: requires-python
Dynamic: summary
